c2d/__init__.py
c2d/capabilities.yml
c2d/cli.py
c2d/commands.py
c2d/config.py
c2d/constants.py
c2d/core.py
c2d/docker.py
c2d/packaging.py
c2d/version.py
artefacts_c2d-1.8.10.dist-info/METADATA
artefacts_c2d-1.8.10.dist-info/WHEEL
artefacts_c2d-1.8.10.dist-info/entry_points.txt
artefacts_c2d-1.8.10.dist-info/top_level.txt
artefacts_c2d-1.8.10.dist-info/RECORD
