Metadata-Version: 2.4
Name: artefacts_c2d
Version: 1.8.10
Author-email: TN <tomo@artefacts.com>, EP <eric@artefacts.com>
Project-URL: Homepage, https://github.com/art-e-fact/c2d
Project-URL: Bug Tracker, https://github.com/art-e-fact/c2d
Project-URL: Changelog, https://github.com/art-e-fact/c2d/CHANGELOG.md
Classifier: Programming Language :: Python :: 3
Classifier: License :: OSI Approved :: Apache Software License
Classifier: Operating System :: OS Independent
Requires-Python: >=3.8
Requires-Dist: pyyaml>=6.0
Provides-Extra: dev
Requires-Dist: awscli; extra == "dev"
Requires-Dist: boto3; extra == "dev"
Requires-Dist: build; extra == "dev"
Requires-Dist: pytest; extra == "dev"
Requires-Dist: pytest-cov; extra == "dev"
Requires-Dist: pytest-env; extra == "dev"
Requires-Dist: pytest-mock; extra == "dev"
Requires-Dist: ruff>=0.9.2; extra == "dev"
Requires-Dist: setuptools_scm; extra == "dev"
Requires-Dist: twine; extra == "dev"
